nezha_agent/__init__.py
nezha_agent/__main__.py
nezha_agent/core/__init__.py
nezha_agent/core/common/__init__.py
nezha_agent/core/common/utils/__init__.py
nezha_agent/core/context/__init__.py
nezha_agent/core/context/context_engine.py
nezha_agent/core/models/__init__.py
nezha_agent/core/models/llm_interface.py
nezha_agent/core/security/__init__.py
nezha_agent/core/security/security.py
nezha_agent/core/tools/__init__.py
nezha_agent/core/tools/base.py
nezha_agent/core/tools/tool_registry.py
nezha_agent/features/__init__.py
nezha_agent/features/agent/__init__.py
nezha_agent/features/agent/agent.py
nezha_agent/features/agent/agent_tool_bridge.py
nezha_agent/features/commands/__init__.py
nezha_agent/features/commands/chat_command.py
nezha_agent/features/commands/plan_command.py
nezha_agent/features/editing/__init__.py
nezha_agent/features/editing/file_io.py
nezha_agent/features/git/__init__.py
nezha_agent/features/git/git_tools.py
nezha_agent/features/shell/__init__.py
nezha_agent/features/shell/shell.py
nezha_agent/features/tools/__init__.py
nezha_agent/features/tools/base.py
nezha_agent/features/tools/file_io.py
nezha_agent/features/tools/git_tools.py
nezha_agent/features/tools/navigation.py
nezha_agent/features/tools/search.py
nezha_agent/features/tools/secure_tools.py
nezha_agent/features/tools/shell.py
nezha_agent/integrations/__init__.py
nezha_agent/integrations/api/__init__.py
nezha_agent/integrations/editors/__init__.py
nezha_agent/integrations/external/__init__.py
nezha_agent/integrations/external/navigation.py
nezha_agent/integrations/external/search.py
nezha_agent/integrations/external/secure_tools.py
nezha_agent/integrations/shells/__init__.py
nezha_agent/plugins/__init__.py
nezha_agent/plugins/registry/__init__.py
nezha_agent/plugins/sdk/__init__.py
nezha_agent/ui/__init__.py
nezha_agent/ui/cli/__init__.py
nezha_agent/ui/cli/__main__.py
nezha_agent/ui/cli/cli.py
nezha_agent/ui/display/__init__.py
nezha_agent/ui/terminal/__init__.py
nezha_agent-0.4.0.dist-info/METADATA
nezha_agent-0.4.0.dist-info/WHEEL
nezha_agent-0.4.0.dist-info/entry_points.txt
nezha_agent-0.4.0.dist-info/top_level.txt
nezha_agent-0.4.0.dist-info/RECORD
