Metadata-Version: 2.4
Name: nezha-agent
Version: 0.4.0
Summary: 基于大语言模型的命令行代码助手
Author-email: ByteDance <example@bytedance.com>
Classifier: Development Status :: 3 - Alpha
Classifier: Intended Audience :: Developers
Classifier: Programming Language :: Python :: 3
Classifier: Programming Language :: Python :: 3.8
Classifier: Programming Language :: Python :: 3.9
Classifier: Programming Language :: Python :: 3.10
Requires-Python: >=3.8
Requires-Dist: typer
Requires-Dist: rich
Requires-Dist: pyyaml
Requires-Dist: platformdirs
Requires-Dist: openai>=1.0.0
Requires-Dist: requests
Provides-Extra: dev
Requires-Dist: pytest>=6.0; extra == "dev"
Requires-Dist: black; extra == "dev"
Requires-Dist: isort; extra == "dev"
Requires-Dist: mypy; extra == "dev"
Requires-Dist: pylint; extra == "dev"
